{"hash":"b2b4302c618342767cb20d0ac9ad1d0bcd8780c0","data":{"services":{"edges":[{"node":{"id":"2a79d5c2a5574c1744ac438a9eeb46b0","title":"Lotocar","status":"construction","link":"https://www.lotocar.fr","repository":"https://github.com/DavidBruant/lotocar","stats_url":"","contact":"contact@lotocar.fr","mission":"Permettre aux personnes isolées et parfois coupées d'internet de se déplacer sur les territoires peu denses","path":"/services/lotocar/"}},{"node":{"id":"9de7d32a1d895ae0c77624e52d1d11e4","title":"Histologe","status":"construction","link":"","repository":"","stats_url":"","contact":"alban.sestiaa@beta.gouv.fr","mission":"Le Contrôle Technique Gratuit du Logement","path":"/services/histologe/"}},{"node":{"id":"ce124f8fb2af62529f12c6feb5cf4fc6","title":"Aidants Connect","status":"construction","link":"https://aidantsconnect.beta.gouv.fr","repository":"https://github.com/betagouv/Aidants_Connect","stats_url":"https://aidantsconnect.beta.gouv.fr/stats/","contact":"aidantsconnect@beta.gouv.fr","mission":"Permettre à un aidant professionnel de réaliser des démarches administratives en ligne à la place d’une personne ne parvenant pas à les faire seule.","path":"/services/aidants-connect/"}}]}},"context":{}}